{
  "project_info": {
    "project_number": "715131919811",
    "project_id": "scheme-suvidha-admin",
    "storage_bucket": "scheme-suvidha-admin.appspot.com"
  },
  "client": [
    {
      "client_info": {
        "mobilesdk_app_id": "1:715131919811:android:c796e635d0c143e619b176",
        "android_client_info": {
          "package_name": "com.example.scheme"
        }
      },
      "oauth_client": [
        {
          "client_id": "715131919811-qagvgqgofqvpvckn17nvtsvfc5hs2aev.apps.googleusercontent.com",
          "client_type": 3
        }
      ],
      "api_key": [
        {
          "current_key": "AIzaSyBx2wVzppvOalchbvIiE2sR9sVKN_-ATFY"
        }
      ],
      "services": {
        "appinvite_service": {
          "other_platform_oauth_client": [
            {
              "client_id": "715131919811-qagvgqgofqvpvckn17nvtsvfc5hs2aev.apps.googleusercontent.com",
              "client_type": 3
            }
          ]
        }
      }
    }
  ],
  "configuration_version": "1"
}